[{"pk": 1, "model": "cms.articletext", "fields": {"body": "<p>Lorem ipsum dolor sit amet, consectetur adipiscing elit. Fusce turpis magna, placerat non dapibus nec, porttitor a nunc. Donec consectetur pharetra rutrum. Praesent ipsum urna, egestas tristique tincidunt eget, vestibulum in sapien.</p>\r\n<p>Phasellus dapibus elementum mi, ut condimentum tortor eleifend ac. Morbi varius molestie elit ac porta. Maecenas at accumsan erat. Pellentesque ut rutrum quam. Morbi tincidunt, neque eu bibendum vehicula, mi nibh molestie purus, sit amet dapibus neque mauris vitae lectus. Cum sociis natoque penatibus et magnis dis parturient montes, nascetur ridiculus mus. Ut eget rhoncus diam. Sed eget lacus urna. Fusce non lorem sit amet massa volutpat ultrices vitae eget arcu. Cras porttitor ultrices eros, a sodales nisl pellentesque a. Praesent velit erat, auctor quis egestas ut, ultrices eu leo. Etiam placerat sapien id tellus lacinia semper. Morbi lobortis pulvinar pulvinar.</p>", "image_alt_text": "A lantern making workshop", "image_body_url": "workshop.jpg"}}, {"pk": 6, "model": "cms.articletext", "fields": {"body": "<p>There was a time it seemed as though<br /> My life was tossing to and fro<br /> And I, left with nowhere to go,<br /> Was subject to the sea.</p>\r\n<p>But there, ahead, a beam of light<br /> Peered through the darkness of the night<br /> And granted to me clearer sight<br /> That I might be set free.</p>\r\n<p>I steered a course toward the land<br /> To find a refuge on the sand<br /> And maybe touch the gentle hand<br /> That guided me along.</p>\r\n<p>And when I reached the coast that night,<br /> Upon a hill, the shining light<br /> Was tended by a welcome sight . . .<br /> My friends had led me home.</p>", "image_alt_text": "", "image_body_url": ""}}, {"pk": 7, "model": "cms.articletext", "fields": {"body": "<p>TO DO!</p>", "image_alt_text": "", "image_body_url": ""}}]